sparkfly/__init__.py
sparkfly/client.py
sparkfly/py.typed
sparkfly_api_client/__init__.py
sparkfly_api_client/api_client.py
sparkfly_api_client/api_response.py
sparkfly_api_client/configuration.py
sparkfly_api_client/exceptions.py
sparkfly_api_client/rest.py
sparkfly_api_client/api/__init__.py
sparkfly_api_client/api/audiences_api.py
sparkfly_api_client/api/authentication_api.py
sparkfly_api_client/api/bi_store_lists_api.py
sparkfly_api_client/api/campaigns_api.py
sparkfly_api_client/api/ctm_api.py
sparkfly_api_client/api/eligible_item_sets_api.py
sparkfly_api_client/api/email_opt_in_api.py
sparkfly_api_client/api/impressions_api.py
sparkfly_api_client/api/items_api.py
sparkfly_api_client/api/member_privacy_api.py
sparkfly_api_client/api/members_api.py
sparkfly_api_client/api/offer_lists_api.py
sparkfly_api_client/api/offer_pos_offer_codes_api.py
sparkfly_api_client/api/offer_states_api.py
sparkfly_api_client/api/offers_api.py
sparkfly_api_client/api/pos_offer_codes_api.py
sparkfly_api_client/api/store_lists_api.py
sparkfly_api_client/api/stores_api.py
sparkfly_api_client/api/templates_api.py
sparkfly_api_client/models/__init__.py
sparkfly_api_client/models/api_error.py
sparkfly_api_client/models/audience.py
sparkfly_api_client/models/bi_store_list.py
sparkfly_api_client/models/bi_store_list_store_lists_inner.py
sparkfly_api_client/models/campaign_request.py
sparkfly_api_client/models/campaign_request_campaign.py
sparkfly_api_client/models/campaign_response.py
sparkfly_api_client/models/campaign_response_campaign.py
sparkfly_api_client/models/campaign_tags_response.py
sparkfly_api_client/models/clark_and_riggs_index_body.py
sparkfly_api_client/models/clark_and_riggs_product_create_body.py
sparkfly_api_client/models/clark_and_riggs_product_response_body.py
sparkfly_api_client/models/clark_and_riggs_product_response_body_clark_and_riggs_product.py
sparkfly_api_client/models/clark_and_riggs_product_response_body_clark_and_riggs_product_offer.py
sparkfly_api_client-1.1.4.dist-info/METADATA
sparkfly_api_client-1.1.4.dist-info/WHEEL
sparkfly_api_client-1.1.4.dist-info/top_level.txt
sparkfly_api_client-1.1.4.dist-info/RECORD
