Metadata-Version: 2.1
Name: sparkfly-api-client
Version: 1.1.4
Summary: Core Operations
Home-page: https://github.com/growth-operations/sparkfly-api-client
Author: Sparkfly Support Team
Author-email: Sparkfly Support Team <support@sparkfly.com>
License: Contact Sparkfly Support for
Project-URL: Repository, https://github.com/GIT_USER_ID/GIT_REPO_ID
Keywords: OpenAPI,OpenAPI-Generator,Core Operations
Requires-Python: >=3.9
Requires-Dist: urllib3 <3.0.0,>=2.1.0
Requires-Dist: python-dateutil >=2.8.2
Requires-Dist: aiohttp >=3.8.4
Requires-Dist: aiohttp-retry >=2.8.3
Requires-Dist: pydantic >=2
Requires-Dist: typing-extensions >=4.7.1
